fmatx/__init__.py
fmatx/_algebraic.py
fmatx/_version.py
fmatx/core.py
fmatx/ctx.py
fmatx/errors.py
fmatx/lipro.py
fmatx/numbers.py
fmatx/test.py
fmatx-0.2.1.dist-info/LICENSE
fmatx-0.2.1.dist-info/METADATA
fmatx-0.2.1.dist-info/WHEEL
fmatx-0.2.1.dist-info/top_level.txt
fmatx-0.2.1.dist-info/RECORD
