Metadata-Version: 2.1
Name: fmatx
Version: 0.2.1
Summary: A full accuracy matrix pure Python implementation.
Author-email: hibays <hibays@email.com>
License: GNU GENERAL PUBLIC LICENSE
Project-URL: documentation, https://readthedocs.org
Project-URL: repository, https://github.com/hibays/fmatx.git
Keywords: matrix,Pure Python,full accuracy,math
Classifier: Programming Language :: Python :: 3
Requires-Python: >=3.6
License-File: LICENSE
